grizzly_ls/__init__.py
grizzly_ls/__main__.py
grizzly_ls/__version__.py
grizzly_ls/cli.py
grizzly_ls/constants.py
grizzly_ls/model.py
grizzly_ls/py.typed
grizzly_ls/text.py
grizzly_ls/utils.py
grizzly_ls/server/__init__.py
grizzly_ls/server/commands.py
grizzly_ls/server/inventory.py
grizzly_ls/server/progress.py
grizzly_ls/server/features/__init__.py
grizzly_ls/server/features/code_actions.py
grizzly_ls/server/features/completion.py
grizzly_ls/server/features/definition.py
grizzly_ls/server/features/diagnostics.py
grizzly_loadtester_ls-2.1.21.dist-info/METADATA
grizzly_loadtester_ls-2.1.21.dist-info/WHEEL
grizzly_loadtester_ls-2.1.21.dist-info/entry_points.txt
grizzly_loadtester_ls-2.1.21.dist-info/RECORD
