Metadata-Version: 2.4
Name: grizzly-loadtester-ls
Version: 2.1.21
Summary: LSP server implementation for grizzly-loadtester load scenario development
Project-URL: Documentation, https://biometria-se.github.io/grizzly/editor-support/
Project-URL: Code, https://github.com/biometria-se/grizzly/
Project-URL: Tracker, https://github.com/Biometria-se/grizzly/issues
Author-email: biometria <opensource@biometria.se>
Maintainer-email: Mikael Göransson <github@mgor.se>
License-Expression: MIT
Keywords: behave,grizzly,grizzly-loadtester,load,loadtest,locust,lsp,performance,traffic generator,vscode
Classifier: Development Status :: 4 - Beta
Classifier: License :: OSI Approved :: MIT License
Classifier: Natural Language :: English
Classifier: Programming Language :: Python
Classifier: Programming Language :: Python :: 3 :: Only
Classifier: Programming Language :: Python :: 3.10
Classifier: Programming Language :: Python :: 3.11
Classifier: Programming Language :: Python :: 3.12
Classifier: Programming Language :: Python :: 3.13
Classifier: Programming Language :: Python :: Implementation :: CPython
Requires-Python: >=3.10
Requires-Dist: colorama>=0.4.6
Requires-Dist: grizzly-loadtester-common
Requires-Dist: ordered-set>=4.1.0
Requires-Dist: pip>=25.2
Requires-Dist: pygls>=1.3.1
Requires-Dist: random-word>=1.0.13
